LICENSE.txt
MANIFEST.in
README.rst
setup.cfg
setup.py
FileSorter.egg-info/PKG-INFO
FileSorter.egg-info/SOURCES.txt
FileSorter.egg-info/dependency_links.txt
FileSorter.egg-info/entry_points.txt
FileSorter.egg-info/requires.txt
FileSorter.egg-info/top_level.txt
data/.DS_Store
data/extensions.json
file_sort/__init__.py
file_sort/extensions.json