Metadata-Version: 1.1
Name: FileSorter
Version: 0.1.9
Summary: A Python file sorter by common data types
Home-page: https://github.com/migetman9/file_sort
Author: Daniel Alexander Ross Evans
Author-email: me@danielarevans.com
License: MIT
Keywords: sorting files file sort
Platform: UNKNOWN
Classifier: Development Status :: 3 - Alpha
Classifier: Intended Audience :: Developers
Classifier: Topic :: Software Development :: Build Tools
Classifier: License :: OSI Approved :: MIT License
Classifier: Programming Language :: Python :: 2
Classifier: Programming Language :: Python :: 2.7
